timeclock/__init__.py
timeclock/__version__
timeclock/api.py
timeclock/cli.py
timeclock/config.py
timeclock/logs.py
cskytimeclock-0.2.1.dist-info/LICENSE
cskytimeclock-0.2.1.dist-info/METADATA
cskytimeclock-0.2.1.dist-info/WHEEL
cskytimeclock-0.2.1.dist-info/entry_points.txt
cskytimeclock-0.2.1.dist-info/top_level.txt
cskytimeclock-0.2.1.dist-info/RECORD
