Metadata-Version: 2.1
Name: cskytimeclock
Version: 0.2.1
Summary: Employees Only Command Line Interface and python API for saving Concentric Sky time entries to timeclock
Home-page: UNKNOWN
Author: Concentric Sky
Author-email: notto@concentricsky.com
License: UNKNOWN
Project-URL: Concentric Sky Careers, https://www.concentricsky.com/team/careers
Platform: UNKNOWN
Classifier: Development Status :: 3 - Alpha
Classifier: Intended Audience :: Developers
Classifier: License :: OSI Approved :: MIT License
Classifier: Programming Language :: Python :: 3
Classifier: Programming Language :: Python :: 3.6
Classifier: Programming Language :: Python :: 3.7
Classifier: Programming Language :: Python :: 3.8
Classifier: Programming Language :: Python :: 3 :: Only
Requires-Python: >=3.6, <4
Requires-Dist: click (~=7.1)
Requires-Dist: requests (~=2.24)
Requires-Dist: six (~=1.15)
Provides-Extra: dev
Requires-Dist: pytest (~=6.0) ; extra == 'dev'
Requires-Dist: responses (~=0.12) ; extra == 'dev'
